hal/__init__.py
python_hal-1.0.0.dist-info/METADATA
python_hal-1.0.0.dist-info/WHEEL
python_hal-1.0.0.dist-info/top_level.txt
python_hal-1.0.0.dist-info/RECORD
