Metadata-Version: 2.1
Name: python-hal
Version: 1.0.0
Summary: H.A.L Is a voice activated virtual assistant
Home-page: UNKNOWN
Author: Cyber Coding
Author-email: <kinectcode@gmail.com>
License: UNKNOWN
Keywords: python,hal,assistant,voice controlled,voice,text to speech
Platform: UNKNOWN
Classifier: Development Status :: 5 - Production/Stable
Classifier: Intended Audience :: Developers
Classifier: Programming Language :: Python :: 3
Classifier: Operating System :: Unix
Classifier: Operating System :: MacOS :: MacOS X
Classifier: Operating System :: Microsoft :: Windows
Requires-Dist: SpeechRecognition
Requires-Dist: argparse
Requires-Dist: art
Requires-Dist: bs4
Requires-Dist: datetime
Requires-Dist: gtts
Requires-Dist: mutagen
Requires-Dist: pygame
Requires-Dist: python-dotenv
Requires-Dist: requests
Requires-Dist: wikipedia
